CHANGES.rst
CONTRIBUTORS.rst
MANIFEST.in
README.rst
setup.cfg
setup.py
docs/LICENSE.GPL
docs/LICENSE.rst
docs/index.rst
src/medialog/.DS_Store
src/medialog/__init__.py
src/medialog.captchawidget.egg-info/PKG-INFO
src/medialog.captchawidget.egg-info/SOURCES.txt
src/medialog.captchawidget.egg-info/dependency_links.txt
src/medialog.captchawidget.egg-info/entry_points.txt
src/medialog.captchawidget.egg-info/namespace_packages.txt
src/medialog.captchawidget.egg-info/not-zip-safe
src/medialog.captchawidget.egg-info/requires.txt
src/medialog.captchawidget.egg-info/top_level.txt
src/medialog/captchawidget/.DS_Store
src/medialog/captchawidget/__init__.py
src/medialog/captchawidget/behavior.py
src/medialog/captchawidget/behaviors.zcml
src/medialog/captchawidget/configure.zcml
src/medialog/captchawidget/interfaces.py
src/medialog/captchawidget/setuphandlers.py
src/medialog/captchawidget/testing.py
src/medialog/captchawidget/locales/medialog.captchawidget.pot
src/medialog/captchawidget/locales/update.sh
src/medialog/captchawidget/profiles/.DS_Store
src/medialog/captchawidget/profiles/default/browserlayer.xml
src/medialog/captchawidget/profiles/default/medialogcaptchawidget_default.txt
src/medialog/captchawidget/profiles/default/metadata.xml
src/medialog/captchawidget/profiles/default/registry.xml
src/medialog/captchawidget/profiles/uninstall/browserlayer.xml
src/medialog/captchawidget/profiles/uninstall/medialogcaptchawidget_uninstall.txt
src/medialog/captchawidget/tests/__init__.py
src/medialog/captchawidget/tests/test_kast.py
src/medialog/captchawidget/tests/test_robot.py
src/medialog/captchawidget/tests/test_setup.py
src/medialog/captchawidget/tests/robot/test_example.robot
src/medialog/captchawidget/tests/robot/test_kast.robot
src/medialog/captchawidget/widgets/.DS_Store
src/medialog/captchawidget/widgets/__init__.py
src/medialog/captchawidget/widgets/captcha_display.pt
src/medialog/captchawidget/widgets/captcha_input.pt
src/medialog/captchawidget/widgets/configure.zcml
src/medialog/captchawidget/widgets/widget.py