Metadata-Version: 1.1
Name: medialog.captchawidget
Version: 1.0a1
Summary: Captcha widget for Dexterity / Plone
Home-page: https://pypi.python.org/pypi/medialog.captchawidget
Author: Espen Moe-Nilssen
Author-email: espen@medialog.no
License: GPL version 2
Keywords: Python Plone
Platform: UNKNOWN
Classifier: Environment :: Web Environment
Classifier: Framework :: Plone
Classifier: Framework :: Plone :: 5.0
Classifier: Programming Language :: Python
Classifier: Programming Language :: Python :: 2.7
Classifier: Operating System :: OS Independent
Classifier: License :: OSI Approved :: GNU General Public License v2 (GPLv2)
